rupee/__init__.py
rupee/decorator.py
rupee/engine.py
rupee/event.py
rupee/tests/__init__.py
rupee/tests/test_decorator.py
rupee/tests/test_engine.py
rupee-0.0.1.dist-info/DESCRIPTION.rst
rupee-0.0.1.dist-info/METADATA
rupee-0.0.1.dist-info/RECORD
rupee-0.0.1.dist-info/WHEEL
rupee-0.0.1.dist-info/metadata.json
rupee-0.0.1.dist-info/top_level.txt
