Metadata-Version: 2.0
Name: rupee
Version: 0.0.1
Summary: A fully-featured cache for Python applications.
Home-page: https://github.com/tmacwill/rupee
Author: Tommy MacWilliam
Author-email: tmacwilliam@cs.harvard.edu
License: MIT
Keywords: cache caching redis memcache memcached
Platform: UNKNOWN
Classifier: Development Status :: 4 - Beta
Classifier: License :: OSI Approved :: MIT License
Classifier: Intended Audience :: Developers
Classifier: Programming Language :: Python :: 3 :: Only
